pysatMagVect/__init__.py
pysatMagVect/_core.py
pysatMagVect/igrf.cpython-38-darwin.so
pysatMagVect/satellite.py
pysatMagVect/version.txt
pysatMagVect/.dylibs/libgcc_s.1.dylib
pysatMagVect/.dylibs/libgfortran.4.dylib
pysatMagVect/.dylibs/libquadmath.0.dylib
pysatMagVect/igrf.cpython-38-darwin.so.dSYM/Contents/Info.plist
pysatMagVect/igrf.cpython-38-darwin.so.dSYM/Contents/Resources/DWARF/igrf.cpython-38-darwin.so
pysatMagVect/tests/__init__.py
pysatMagVect/tests/test_core.py
pysatMagVect-0.4.0.dist-info/LICENSE
pysatMagVect-0.4.0.dist-info/METADATA
pysatMagVect-0.4.0.dist-info/RECORD
pysatMagVect-0.4.0.dist-info/top_level.txt
pysatMagVect-0.4.0.dist-info/WHEEL
